Metadata-Version: 2.1
Name: ativ-pacotes
Version: 0.0.1
Summary: Repositório para atividade de sala, contendo módulos consulta; armazenamento; interacao
Author: Arthur Queiroz
Author-email: arthur21070032@aluno.cesupa.br
License: MIT License
Keywords: ativ pacotes
License-File: LICENSE
